docstr/__init__.py
docstr/configargparse.py
docstr/docstring.py
docstr/meta.py
docstr/params.py
docstr/parsing.py
docstr/cli/__init__.py
docstr/cli/cli.py
docstr/cli/io.py
docstr/pipeline/__init__.py
docstr/pipeline/generator.py
docstr/pipeline/parse.py
docstr/pipeline/yaml.py
docstr-0.0.2.dist-info/LICENSE.txt
docstr-0.0.2.dist-info/METADATA
docstr-0.0.2.dist-info/WHEEL
docstr-0.0.2.dist-info/entry_points.txt
docstr-0.0.2.dist-info/top_level.txt
docstr-0.0.2.dist-info/RECORD
