Metadata-Version: 2.1
Name: docstr
Version: 0.0.2
Summary: Docstring parsing for generating argument and config parsers and expediting the common coding processes.
Home-page: https://github.com/prijatelj/docstr
Author: Derek S. Prijatelj
Author-email: dprijate@nd.edu
License: UNKNOWN
Platform: UNKNOWN
Classifier: Programming Language :: Python :: 3
Classifier: License :: OSI Approved :: MIT License
Classifier: Operating System :: OS Independent
Requires-Python: >=3.7
License-File: LICENSE.txt
Requires-Dist: PyYAML
Requires-Dist: docutils
Requires-Dist: Sphinx
Requires-Dist: ConfigArgParse
